Workbook
Name aporte: 'FIIs Controls'!$D$18
Name Dividendos_mensais: 'FIIs Controls'!$D$22
Name patrimonio: 'FIIs Controls'!$D$21
Name perfil: 'FIIs Controls'!$C$33
Name perfil_investidor: 'FIIs Controls'!$C$33
Name qtd_anos: 'FIIs Controls'!$D$19
Name rendimento_carteira: 'FIIs Controls'!$D$14
Name salario: 'FIIs Controls'!$D$13
Name sugestao_investimento: 'FIIs Controls'!$C$15
Name sungestao: 'FIIs Controls'!$D$15
Name sungestao_investimento: 'FIIs Controls'!$D$15
Name taxa_mensal: 'FIIs Controls'!$D$20

Sheet Perguntas de Negócio
B2: 1 | C2: Quanto investir por mês ?
B3: 2 | C3: Por Quantos Anos ?
B4: 3 | C4: Taxa de Rendimento Mensal
B5: 4 | C5: Quanto de Patrimônio Acumulado ?
B6: 5 | C6: Quanto que é os Dividendos Mensais ?

Sheet Dashboard

Sheet FIIs Controls
B12: CONFIGURAÇÕES
B13: Salario | D13: 3950
B14: Rendimento Carteira | D14: 0.006
B15: Sugentão de Investimento | C15: 0.3 | D15: =salario*sugestao_investimento -> 1185
B17: INVESTIMENTO MENSAL
B18: Quanto investir por mês ? | D18: 1185
B19: Por Quantos Anos ? | D19: 5
B20: Taxa de Rendimento Mensal | D20: 0.01079 | E20: total do aporte
B21: Patrimônio Acumulado ? | D21: =FV(taxa_mensal,qtd_anos*12,aporte*-1) -> 99275.643 | E21: =aporte*(qtd_anos*12) -> 71100
B22: Dividendos Mensais ? | D22: =patrimonio*rendimento_carteira -> 595.65386
B24: Cenários | D24: Dividendos
A25: 2 | B25: Quantos em 2 Anos ? | C25: =FV($D$20,$A25*12,$D$18*-1) -> 32264.738 | D25: =C25*rendimento_carteira -> 193.58843
A26: 5 | B26: Quantos em 5 Anos ? | C26: =FV($D$20,$A26*12,$D$18*-1) -> 99275.643 | D26: =C26*rendimento_carteira -> 595.65386
A27: 10 | B27: Quantos em 10 Anos ? | C27: =FV($D$20,$A27*12,$D$18*-1) -> 288291.79 | D27: =C27*rendimento_carteira -> 1729.7508
A28: 20 | B28: Quantos em 20 Anos ? | C28: =FV($D$20,$A28*12,$D$18*-1) -> 1333360.1 | D28: =C28*rendimento_carteira -> 8000.1606
A29: 30 | B29: Quantos em 30 Anos ? | C29: =FV($D$20,$A29*12,$D$18*-1) -> 5121771 | D29: =C29*rendimento_carteira -> 30730.626
B33: PERFIL | C33: Agressivo
B34: VALOR A SER INVESTIDO POR MÊS | C34: =aporte -> 1185
B36: TIPO DE FII | C36: Percentual Surgerido | D36: Valores
B37: PAPEL | C37: =VLOOKUP(perfil_investidor&"-"&B37,'Tabelas de Apoio'!$A:$D,4,FALSE) -> 0.5 | D37: =C37*$C$34 -> 592.5
B38: TIJOLO | C38: =VLOOKUP(perfil_investidor&"-"&B38,'Tabelas de Apoio'!$A:$D,4,FALSE) -> 0.1 | D38: =C38*$C$34 -> 118.5
B39: HÍBRIDO | C39: =VLOOKUP(perfil_investidor&"-"&B39,'Tabelas de Apoio'!$A:$D,4,FALSE) -> 0.05 | D39: =C39*$C$34 -> 59.25
B40: FOFs | C40: =VLOOKUP(perfil_investidor&"-"&B40,'Tabelas de Apoio'!$A:$D,4,FALSE) -> 0.05 | D40: =C40*$C$34 -> 59.25
B41: DESENVOLVIMENTO | C41: =VLOOKUP(perfil_investidor&"-"&B41,'Tabelas de Apoio'!$A:$D,4,FALSE) -> 0.2 | D41: =C41*$C$34 -> 237
B42: HOTELARIAS | C42: =VLOOKUP(perfil_investidor&"-"&B42,'Tabelas de Apoio'!$A:$D,4,FALSE) -> 0.1 | D42: =C42*$C$34 -> 118.5
D43: =SUM(D37:D42) -> 1185

Sheet Tabelas de Apoio
A3: CHAVE | B3: PERFIL | C3: TIPO DE FII | D3: %
A4: =B4&"-"&C4 -> Conservador-PAPEL | B4: Conservador | C4: PAPEL | D4: 0.3 | H4: %
A5: =B5&"-"&C5 -> Conservador-TIJOLO | B5: Conservador | C5: TIJOLO | D5: 0.5 | G5: Moderado-TIJOLO | H5: =VLOOKUP(G5,$A:$D,4,) -> 0.35
A6: =B6&"-"&C6 -> Conservador-HÍBRIDO | B6: Conservador | C6: HÍBRIDO | D6: 0.1
A7: =B7&"-"&C7 -> Conservador-FOFs | B7: Conservador | C7: FOFs | D7: 0.1
A8: =B8&"-"&C8 -> Conservador-DESENVOLVIMENTO | B8: Conservador | C8: DESENVOLVIMENTO | D8: 0
A9: =B9&"-"&C9 -> Conservador-HOTELARIAS | B9: Conservador | C9: HOTELARIAS | D9: 0
A10: =B10&"-"&C10 -> Moderado-PAPEL | B10: Moderado | C10: PAPEL | D10: 0.32
A11: =B11&"-"&C11 -> Moderado-TIJOLO | B11: Moderado | C11: TIJOLO | D11: 0.35
A12: =B12&"-"&C12 -> Moderado-HÍBRIDO | B12: Moderado | C12: HÍBRIDO | D12: 0.08
A13: =B13&"-"&C13 -> Moderado-FOFs | B13: Moderado | C13: FOFs | D13: 0.05
A14: =B14&"-"&C14 -> Moderado-DESENVOLVIMENTO | B14: Moderado | C14: DESENVOLVIMENTO | D14: 0.1
A15: =B15&"-"&C15 -> Moderado-HOTELARIAS | B15: Moderado | C15: HOTELARIAS | D15: 0.1
A16: =B16&"-"&C16 -> Agressivo-PAPEL | B16: Agressivo | C16: PAPEL | D16: 0.5
A17: =B17&"-"&C17 -> Agressivo-TIJOLO | B17: Agressivo | C17: TIJOLO | D17: 0.1
... A21: =B21&"-"&C21 -> Agressivo-HOTELARIAS | B21: Agressivo | C21: HOTELARIAS | D21: 0.1
